ciscoaxlJFK/__int__.py
ciscoaxlJFK/axl.py
ciscounityapi/__init__.py
ciscounityapi/api.py
src/ciscoaxlJFK/__int__.py
src/ciscoaxlJFK/axl.py
ciscounityapi-0.0.1.dist-info/LICENSE
ciscounityapi-0.0.1.dist-info/METADATA
ciscounityapi-0.0.1.dist-info/WHEEL
ciscounityapi-0.0.1.dist-info/top_level.txt
ciscounityapi-0.0.1.dist-info/RECORD
